aws_cli_migrate/__init__.py
aws_cli_migrate/cli.py
aws_cli_migrate/linter.py
aws_cli_migrate/rules/__init__.py
aws_cli_migrate/rules/base.py
aws_cli_migrate/rules/binary_params_base64.py
aws_cli_migrate/rules/cli_input_json.py
aws_cli_migrate/rules/default_pager.py
aws_cli_migrate/rules/deploy_empty_changeset.py
aws_cli_migrate/rules/ecr_get_login.py
aws_cli_migrate/rules/hidden_aliases.py
aws_cli_migrate/rules/s3_copies.py
aws_cli_migrate/rules/utils.py
aws_cli_migrate-1.0.0.dist-info/licenses/LICENSE
aws_cli_migrate-1.0.0.dist-info/licenses/NOTICE
aws_cli_migrate-1.0.0.dist-info/METADATA
aws_cli_migrate-1.0.0.dist-info/WHEEL
aws_cli_migrate-1.0.0.dist-info/entry_points.txt
aws_cli_migrate-1.0.0.dist-info/top_level.txt
aws_cli_migrate-1.0.0.dist-info/RECORD
