Metadata-Version: 2.4
Name: aws-cli-migrate
Version: 1.0.0
Summary: Command-line tool to lint and modify bash scripts that use AWS CLI v1 to prevent breakage from changes introduced in AWS CLI v2.
License-Expression: Apache-2.0
Project-URL: Homepage, https://github.com/aws/aws-cli
Project-URL: Bug Tracker, https://github.com/aws/aws-cli/issues
Project-URL: Documentation, https://github.com/aws/aws-cli
Project-URL: Source Code, https://github.com/aws/aws-cli
Keywords: aws,cli,linter,bash,script,migration,v1,v2,codemod,migrate
Classifier: Development Status :: 5 - Production/Stable
Classifier: Intended Audience :: Developers
Classifier: Intended Audience :: System Administrators
Classifier: Natural Language :: English
Classifier: Operating System :: OS Independent
Classifier: Programming Language :: Python :: 3
Classifier: Programming Language :: Python :: 3.9
Classifier: Programming Language :: Python :: 3.10
Classifier: Programming Language :: Python :: 3.11
Classifier: Programming Language :: Python :: 3.12
Classifier: Programming Language :: Python :: 3.13
Classifier: Topic :: Software Development :: Quality Assurance
Classifier: Topic :: Utilities
Requires-Python: >=3.9
License-File: LICENSE
License-File: NOTICE
Requires-Dist: ast-grep-py==0.40.5
Provides-Extra: dev
Requires-Dist: pytest<8.2.0,>=8.0.0; extra == "dev"
Requires-Dist: ruff<0.14.0,>=0.8.0; extra == "dev"
Dynamic: license-file
